accu/accu/auth/__init__.py
accu/accu/auth/middleware.py
accu/accu/auth/mixins.py
accu/accu/auth/tests.py
accu/accu/auth/wraper.py
accu/accu/core/__init__.py
accu/accu/core/config.py
accu/accu/core/settings.py
accu/accu/core/test_config.py
accu/accu/core/test_utils.py
accu/accu/core/test_validators.py
accu/accu/core/utils.py
accu/accu/core/validators.py
accu/accu/core/clean/__init__.py
accu/accu/core/clean/mixin.py
accu/accu/core/clean/svg.py
accu/accu/core/clean/tests.py
accu/accu/core/helpers/__init__.py
accu/accu/core/helpers/clean.py
accu/accu/core/helpers/logging.py
accu/accu/core/helpers/tests.py
accu/accu/core/tasks/__init__.py
accu/accu/core/tasks/general.py
accu/accu/core/tasks/tests.py
accu-0.1a2.dist-info/LICENSE
accu-0.1a2.dist-info/METADATA
accu-0.1a2.dist-info/WHEEL
accu-0.1a2.dist-info/top_level.txt
accu-0.1a2.dist-info/RECORD
