Metadata-Version: 2.1
Name: accu
Version: 0.1a2
Summary: More batteries for Django - an opinionated package
License: MIT
Classifier: Framework :: Django
Classifier: Programming Language :: Python :: 3
License-File: LICENSE
Requires-Dist: django
